{
  "spec": {
    "data": {"url": "data/movies.json"},
    "mark": "?",
    "encodings": [
      {
        "channel": "?",
        "field": "Major_Genre",
        "type": "nominal"
      },{
        "channel": "?",
        "field": "Creative_Type",
        "type": "nominal"
      }
    ]
  },
  "nest": [
    {"groupBy": "fieldTransform"},
    {"groupBy": "encoding", "orderGroupBy": "effectiveness"},
    {"groupBy": "transpose", "orderGroupBy": "effectiveness"}
  ],
  "orderBy": "effectiveness",
  "config": {
    "autoAddCount": true
  }
}